LICENSE
MANIFEST.in
README.md
README.rst
setup.py
test/__init__.py
test/test_emb2vec.py
torch_emb2vec/__init__.py
torch_emb2vec.egg-info/PKG-INFO
torch_emb2vec.egg-info/SOURCES.txt
torch_emb2vec.egg-info/dependency_links.txt
torch_emb2vec.egg-info/requires.txt
torch_emb2vec.egg-info/top_level.txt
torch_emb2vec.egg-info/zip-safe