Metadata-Version: 2.1
Name: torch-emb2vec
Version: 0.1.0
Summary: Convert W2V embeddings of a sequence (2D) to one vector (1D)
Home-page: http://github.com/ulf1/torch-emb2vec
Author: Ulf Hamster
Author-email: 554c46@gmail.com
License: Apache License 2.0
Platform: UNKNOWN
Requires-Python: >=3.6
License-File: LICENSE
